paiflow/VERSION.txt
paiflow/__init__.py
paiflow/info_model.py
paiflow/paiflow.py
paiflow/predict_base.py
paiflow-1.0.10.dist-info/DESCRIPTION.rst
paiflow-1.0.10.dist-info/METADATA
paiflow-1.0.10.dist-info/RECORD
paiflow-1.0.10.dist-info/WHEEL
paiflow-1.0.10.dist-info/metadata.json
paiflow-1.0.10.dist-info/top_level.txt
