Metadata-Version: 2.0
Name: paiflow
Version: 1.0.10
Summary: pai flow
Home-page: https://bitbucket.org/paiflow/paiflow
Author: ueqt
Author-email: ueqtxu@gmail.com
License: GPL v2
Platform: UNKNOWN
Classifier: Operating System :: MacOS :: MacOS X
Classifier: Operating System :: Microsoft :: Windows
Classifier: Operating System :: POSIX
Classifier: Programming Language :: Python
